london_tube_status/__init__.py
london_tube_status-0.7.dist-info/METADATA
london_tube_status-0.7.dist-info/WHEEL
london_tube_status-0.7.dist-info/top_level.txt
london_tube_status-0.7.dist-info/RECORD
