Metadata-Version: 2.4
Name: london-tube-status
Version: 0.7
Summary: Parse London tube data into a dictionary
Home-page: https://github.com/robmarkcole/London-tube-status
Author: Robin Cole
Author-email: robmarkcole@gmail.com
License: Apache License, Version 2.0
Classifier: Intended Audience :: Developers
Classifier: Natural Language :: English
Classifier: Programming Language :: Python
Classifier: Programming Language :: Python :: 3
Requires-Python: >=3.6
Requires-Dist: aiohttp
Dynamic: author
Dynamic: author-email
Dynamic: classifier
Dynamic: home-page
Dynamic: license
Dynamic: requires-dist
Dynamic: requires-python
Dynamic: summary
